Workbook
Name SegmentaçãodeDados_Categoria: #N/A
Name SegmentaçãodeDados_Mês: #N/A
Name SegmentaçãodeDados_Tipo: #N/A

Sheet Base Financeira
A1: Data | B1: Mês | C1: Tipo | D1: Categoria | E1: Descrição | F1: Valor | G1: Análise
A2: 46023 | B2: Janeiro | C2: Entrada | D2: Salário | E2: Pagamento mensal | F2: 4200 | G2: =IF(F2>1000,"Valor Alto",IF(F2>300,"Valor Médio","Valor Baixo")) -> Valor Alto | I2: Entrada | J2: Salário
A3: 46025 | B3: Janeiro | C3: Saída | D3: Alimentação | E3: Mercado | F3: 650 | G3: =IF(F3>1000,"Valor Alto",IF(F3>300,"Valor Médio","Valor Baixo")) -> Valor Médio | I3: Saída | J3: Alimentação
A4: 46027 | B4: Janeiro | C4: Saída | D4: Transporte | E4: Gasolina | F4: 250 | G4: =IF(F4>1000,"Valor Alto",IF(F4>300,"Valor Médio","Valor Baixo")) -> Valor Baixo | J4: Transporte
A5: 46032 | B5: Janeiro | C5: Saída | D5: Moradia | E5: Aluguel | F5: 1400 | G5: =IF(F5>1000,"Valor Alto",IF(F5>300,"Valor Médio","Valor Baixo")) -> Valor Alto | J5: Moradia
A6: 46037 | B6: Janeiro | C6: Saída | D6: Lazer | E6: Streaming | F6: 55 | G6: =IF(F6>1000,"Valor Alto",IF(F6>300,"Valor Médio","Valor Baixo")) -> Valor Baixo | J6: Saúde
A7: 46042 | B7: Janeiro | C7: Saída | D7: Saúde | E7: Farmácia | F7: 120 | G7: =IF(F7>1000,"Valor Alto",IF(F7>300,"Valor Médio","Valor Baixo")) -> Valor Baixo | J7: Lazer
A8: 46047 | B8: Janeiro | C8: Saída | D8: Educação | E8: Curso online | F8: 180 | G8: =IF(F8>1000,"Valor Alto",IF(F8>300,"Valor Médio","Valor Baixo")) -> Valor Baixo | J8: Educação
A9: 46054 | B9: Fevereiro | C9: Entrada | D9: Salário | E9: Pagamento mensal | F9: 4200 | G9: =IF(F9>1000,"Valor Alto",IF(F9>300,"Valor Médio","Valor Baixo")) -> Valor Alto | J9: Outros
A10: 46057 | B10: Fevereiro | C10: Saída | D10: Alimentação | E10: Mercado | F10: 720 | G10: =IF(F10>1000,"Valor Alto",IF(F10>300,"Valor Médio","Valor Baixo")) -> Valor Médio
A11: 46061 | B11: Fevereiro | C11: Saída | D11: Saúde | E11: Farmácia | F11: 130 | G11: =IF(F11>1000,"Valor Alto",IF(F11>300,"Valor Médio","Valor Baixo")) -> Valor Baixo
A12: 46065 | B12: Fevereiro | C12: Saída | D12: Transporte | E12: Uber | F12: 90 | G12: =IF(F12>1000,"Valor Alto",IF(F12>300,"Valor Médio","Valor Baixo")) -> Valor Baixo
A13: 46069 | B13: Fevereiro | C13: Saída | D13: Moradia | E13: Aluguel | F13: 1400 | G13: =IF(F13>1000,"Valor Alto",IF(F13>300,"Valor Médio","Valor Baixo")) -> Valor Alto
A14: 46073 | B14: Fevereiro | C14: Saída | D14: Educação | E14: Curso online | F14: 180 | G14: =IF(F14>1000,"Valor Alto",IF(F14>300,"Valor Médio","Valor Baixo")) -> Valor Baixo | I14: Receita Total | K14: Despesas Totais | M14: Maior Despesa | O14: Média de Despesas
A15: 46076 | B15: Fevereiro | C15: Saída | D15: Lazer | E15: Cinema | F15: 110 | G15: =IF(F15>1000,"Valor Alto",IF(F15>300,"Valor Médio","Valor Baixo")) -> Valor Baixo | I15: =SUMIF(C:C,"Entrada",F:F) -> 12600 | K15: =SUMIF(C:C,"Saída",F:F) -> 8285 | M15: =_xlfn.MAXIFS(F:F,C:C,"Saída") -> 1400 | O15: =AVERAGEIFS(F:F,C:C,"Saída") -> 460.27778
A16: 46082 | B16: Março | C16: Entrada | D16: Salário | E16: Pagamento mensal | F16: 4200 | G16: =IF(F16>1000,"Valor Alto",IF(F16>300,"Valor Médio","Valor Baixo")) -> Valor Alto
A17: 46084 | B17: Março | C17: Saída | D17: Alimentação | E17: Mercado | F17: 680 | G17: =IF(F17>1000,"Valor Alto",IF(F17>300,"Valor Médio","Valor Baixo")) -> Valor Médio | I17: Saldo Final
A18: 46088 | B18: Março | C18: Saída | D18: Transporte | E18: Gasolina | F18: 300 | G18: =IF(F18>1000,"Valor Alto",IF(F18>300,"Valor Médio","Valor Baixo")) -> Valor Baixo | I18: =I15-K15 -> 4315
A19: 46091 | B19: Março | C19: Saída | D19: Moradia | E19: Aluguel | F19: 1400 | G19: =IF(F19>1000,"Valor Alto",IF(F19>300,"Valor Médio","Valor Baixo")) -> Valor Alto
A20: 46096 | B20: Março | C20: Saída | D20: Saúde | E20: Consulta | F20: 250 | G20: =IF(F20>1000,"Valor Alto",IF(F20>300,"Valor Médio","Valor Baixo")) -> Valor Baixo
A21: 46099 | B21: Março | C21: Saída | D21: Lazer | E21: Restaurante | F21: 220 | G21: =IF(F21>1000,"Valor Alto",IF(F21>300,"Valor Médio","Valor Baixo")) -> Valor Baixo
A22: 46103 | B22: Março | C22: Saída | D22: Outros | E22: Presente | F22: 150 | G22: =IF(F22>1000,"Valor Alto",IF(F22>300,"Valor Médio","Valor Baixo")) -> Valor Baixo

Sheet tabela dinâmica
A1: Tipo | B1: Saída | D1: Soma de Valor | E1: Rótulos de Coluna | I1: Rótulos de Linha | J1: Soma de Valor
D2: Rótulos de Linha | E2: Entrada | F2: Saída | G2: Total Geral | I2: Valor Alto | J2: 16800
A3: Rótulos de Linha | B3: Soma de Valor | D3: Janeiro | E3: 4200 | F3: 2655 | G3: 6855 | I3: Valor Baixo | J3: 2035
A4: Alimentação | B4: 2050 | D4: Fevereiro | E4: 4200 | F4: 2630 | G4: 6830 | I4: Valor Médio | J4: 2050
A5: Educação | B5: 360 | D5: Março | E5: 4200 | F5: 3000 | G5: 7200 | I5: Total Geral | J5: 20885
A6: Lazer | B6: 385 | D6: Total Geral | E6: 12600 | F6: 8285 | G6: 20885
A7: Moradia | B7: 4200
A8: Outros | B8: 150
A9: Saúde | B9: 500
A10: Transporte | B10: 640
A11: Total Geral | B11: 8285

Sheet Dashboard
A1: Receita Total | D1: Despesas Totais | G1: Saldo Final | J1: Maior Despesa | M1: Média de Despesas
A2: ='Base Financeira'!I15 -> 12600 | D2: ='Base Financeira'!K15 -> 8285 | G2: ='Base Financeira'!I18 -> 4315 | J2: ='Base Financeira'!M15 -> 1400 | M2: ='Base Financeira'!O15 -> 460.27778
